{"result_code":"000","addresses":[{"zip":"5013521","address_key":"21205248000","pref":"岐阜県","city":"関市","town":"下之保","region_code":"03","services":[{"category":"g2home","state_summary":"not_providing","details":[{"state":"not_providing"}]},{"category":"g2ms","state_summary":"not_providing","details":[{"state":"not_providing"}]},{"category":"g10home","state_summary":"not_providing","details":[{"state":"not_providing"}]},{"category":"gs10home","state_summary":"not_providing","details":[{"state":"not_providing"}]}]},{"zip":"5013521","address_key":"21205248101","pref":"岐阜県","city":"関市","town":"下之保上野","region_code":"03","services":[{"category":"g2home","state_summary":"not_providing","details":[{"state":"not_providing"}]},{"category":"g2ms","state_summary":"not_providing","details":[{"state":"not_providing"}]},{"category":"g10home","state_summary":"not_providing","details":[{"state":"not_providing"}]},{"category":"gs10home","state_summary":"not_providing","details":[{"state":"not_providing"}]}]},{"zip":"5013521","address_key":"21205248102","pref":"岐阜県","city":"関市","town":"下之保大門","region_code":"03","services":[{"category":"g2home","state_summary":"not_providing","details":[{"state":"not_providing"}]},{"category":"g2ms","state_summary":"not_providing","details":[{"state":"not_providing"}]},{"category":"g10home","state_summary":"not_providing","details":[{"state":"not_providing"}]},{"category":"gs10home","state_summary":"not_providing","details":[{"state":"not_providing"}]}]},{"zip":"5013521","address_key":"21205248103","pref":"岐阜県","city":"関市","town":"下之保轡野","region_code":"03","services":[{"category":"g2home","state_summary":"not_providing","details":[{"state":"not_providing"}]},{"category":"g2ms","state_summary":"not_providing","details":[{"state":"not_providing"}]},{"category":"g10home","state_summary":"not_providing","details":[{"state":"not_providing"}]},{"category":"gs10home","state_summary":"not_providing","details":[{"state":"not_providing"}]}]},{"zip":"5013521","address_key":"21205248104","pref":"岐阜県","city":"関市","town":"下之保古布","region_code":"03","services":[{"category":"g2home","state_summary":"not_providing","details":[{"state":"not_providing"}]},{"category":"g2ms","state_summary":"not_providing","details":[{"state":"not_providing"}]},{"category":"g10home","state_summary":"not_providing","details":[{"state":"not_providing"}]},{"category":"gs10home","state_summary":"not_providing","details":[{"state":"not_providing"}]}]},{"zip":"5013521","address_key":"21205248105","pref":"岐阜県","city":"関市","town":"下之保多良木","region_code":"03","services":[{"category":"g2home","state_summary":"not_providing","details":[{"state":"not_providing"}]},{"category":"g2ms","state_summary":"not_providing","details":[{"state":"not_providing"}]},{"category":"g10home","state_summary":"not_providing","details":[{"state":"not_providing"}]},{"category":"gs10home","state_summary":"not_providing","details":[{"state":"not_providing"}]}]},{"zip":"5013521","address_key":"21205248106","pref":"岐阜県","city":"関市","town":"下之保戸丁","region_code":"03","services":[{"category":"g2home","state_summary":"not_providing","details":[{"state":"not_providing"}]},{"category":"g2ms","state_summary":"not_providing","details":[{"state":"not_providing"}]},{"category":"g10home","state_summary":"not_providing","details":[{"state":"not_providing"}]},{"category":"gs10home","state_summary":"not_providing","details":[{"state":"not_providing"}]}]},{"zip":"5013521","address_key":"21205248107","pref":"岐阜県","city":"関市","town":"下之保百々目木","region_code":"03","services":[{"category":"g2home","state_summary":"not_providing","details":[{"state":"not_providing"}]},{"category":"g2ms","state_summary":"not_providing","details":[{"state":"not_providing"}]},{"category":"g10home","state_summary":"not_providing","details":[{"state":"not_providing"}]},{"category":"gs10home","state_summary":"not_providing","details":[{"state":"not_providing"}]}]},{"zip":"5013521","address_key":"21205248108","pref":"岐阜県","city":"関市","town":"下之保殿村","region_code":"03","services":[{"category":"g2home","state_summary":"not_providing","details":[{"state":"not_providing"}]},{"category":"g2ms","state_summary":"not_providing","details":[{"state":"not_providing"}]},{"category":"g10home","state_summary":"not_providing","details":[{"state":"not_providing"}]},{"category":"gs10home","state_summary":"not_providing","details":[{"state":"not_providing"}]}]},{"zip":"5013521","address_key":"21205248109","pref":"岐阜県","city":"関市","town":"下之保西洞","region_code":"03","services":[{"category":"g2home","state_summary":"not_providing","details":[{"state":"not_providing"}]},{"category":"g2ms","state_summary":"not_providing","details":[{"state":"not_providing"}]},{"category":"g10home","state_summary":"not_providing","details":[{"state":"not_providing"}]},{"category":"gs10home","state_summary":"not_providing","details":[{"state":"not_providing"}]}]},{"zip":"5013521","address_key":"21205248110","pref":"岐阜県","city":"関市","town":"下之保町","region_code":"03","services":[{"category":"g2home","state_summary":"not_providing","details":[{"state":"not_providing"}]},{"category":"g2ms","state_summary":"not_providing","details":[{"state":"not_providing"}]},{"category":"g10home","state_summary":"not_providing","details":[{"state":"not_providing"}]},{"category":"gs10home","state_summary":"not_providing","details":[{"state":"not_providing"}]}]}]}