{"result_code":"000","addresses":[{"zip":"5030000","address_key":"21202014000","pref":"岐阜県","city":"大垣市","town":"浅西町","region_code":"03","services":[{"category":"g2home","state_summary":"not_providing","details":[{"state":"not_providing"}]},{"category":"g2ms","state_summary":"not_providing","details":[{"state":"not_providing"}]},{"category":"g10home","state_summary":"not_providing","details":[{"state":"not_providing"}]},{"category":"gs10home","state_summary":"not_providing","details":[{"state":"not_providing"}]}]},{"zip":"5030000","address_key":"21202055000","pref":"岐阜県","city":"大垣市","town":"上笠町","region_code":"03","services":[{"category":"g2home","state_summary":"not_providing","details":[{"state":"not_providing"}]},{"category":"g2ms","state_summary":"not_providing","details":[{"state":"not_providing"}]},{"category":"g10home","state_summary":"not_providing","details":[{"state":"not_providing"}]},{"category":"gs10home","state_summary":"not_providing","details":[{"state":"not_providing"}]}]},{"zip":"5030000","address_key":"21202117000","pref":"岐阜県","city":"大垣市","town":"多芸島町","region_code":"03","services":[{"category":"g2home","state_summary":"not_providing","details":[{"state":"not_providing"}]},{"category":"g2ms","state_summary":"not_providing","details":[{"state":"not_providing"}]},{"category":"g10home","state_summary":"not_providing","details":[{"state":"not_providing"}]},{"category":"gs10home","state_summary":"not_providing","details":[{"state":"not_providing"}]}]},{"zip":"5030000","address_key":"21202141000","pref":"岐阜県","city":"大垣市","town":"西大外羽町","region_code":"03","services":[{"category":"g2home","state_summary":"not_providing","details":[{"state":"not_providing"}]},{"category":"g2ms","state_summary":"not_providing","details":[{"state":"not_providing"}]},{"category":"g10home","state_summary":"not_providing","details":[{"state":"not_providing"}]},{"category":"gs10home","state_summary":"not_providing","details":[{"state":"not_providing"}]}]},{"zip":"5030000","address_key":"21202149000","pref":"岐阜県","city":"大垣市","town":"野口町","region_code":"03","services":[{"category":"g2home","state_summary":"providing_partially","details":[{"state":"providing"},{"state":"not_providing"}]},{"category":"g2ms","state_summary":"providing_partially","details":[{"state":"providing"},{"state":"not_providing"}]},{"category":"g10home","state_summary":"not_providing","details":[{"state":"not_providing"}]},{"category":"gs10home","state_summary":"not_providing","details":[{"state":"not_providing"}]}]},{"zip":"5030000","address_key":"21202176000","pref":"岐阜県","city":"大垣市","town":"万石町","region_code":"03","services":[{"category":"g2home","state_summary":"providing","details":[{"state":"providing"}]},{"category":"g2ms","state_summary":"providing","details":[{"state":"providing"}]},{"category":"g10home","state_summary":"not_providing","details":[{"state":"not_providing"}]},{"category":"gs10home","state_summary":"not_providing","details":[{"state":"not_providing"}]}]}]}